mmon/__about__.py
mmon/__init__.py
mmon/__main__.py
mmon/config.py
mmon/engine.py
mmon/langchain_callback.py
mmon/tools/__init__.py
mmon-0.12.1.dist-info/METADATA
mmon-0.12.1.dist-info/WHEEL
mmon-0.12.1.dist-info/entry_points.txt
mmon-0.12.1.dist-info/licenses/LICENSE
mmon-0.12.1.dist-info/RECORD
