Metadata-Version: 2.3
Name: mmon
Version: 0.12.1
Summary: A customizable chat bot.
Project-URL: homepage, https://github.com/iaalm/mmon
Project-URL: repository, https://github.com/iaalm/mmon
Project-URL: documentation, https://github.com/iaalm/mmon
Author-email: iaalm <iaalmsimon@gmail.com>
License: MIT
License-File: LICENSE
Keywords: chatbot,llm
Classifier: Development Status :: 4 - Beta
Classifier: Environment :: Console
Classifier: Intended Audience :: Science/Research
Classifier: License :: OSI Approved :: MIT License
Classifier: Programming Language :: Python :: 3 :: Only
Requires-Python: >=3.9
Requires-Dist: colorama
Requires-Dist: langchain-community
Requires-Dist: langchain-openai
Requires-Dist: langchain>=0.1.0
Requires-Dist: loguru
Requires-Dist: numexpr
Requires-Dist: openai>=1.0
Requires-Dist: pydantic
Requires-Dist: tiktoken>=0.5.1
Provides-Extra: dev
Requires-Dist: black; extra == 'dev'
Requires-Dist: build; extra == 'dev'
Requires-Dist: hatch; extra == 'dev'
Requires-Dist: isort; extra == 'dev'
Requires-Dist: mypy; extra == 'dev'
